{"dbDsn":"192.168.5.69:3306","dbName":"new_dog123","dbAuth":"dog123:dog123","sdbDsn":"192.168.5.86:3306","sdbName":"process","sdbAuth":"dog123:dog123","numloops":3,"redisConn":"192.168.5.45:6380,192.168.5.45:6381,192.168.5.220:6380,192.168.5.220:6381,192.168.5.230:6380,192.168.5.230:6381","queueName":"threadHtmlUrl","saveDir":"/www/wwwroot/goumin.com/www/cms/html/bbs.m.goumin.com/","logFile":"/tmp/create_thread.log","logLevel":1,"tidStart":"0","tidEnd":"640900","domain":"http://m.goumin.com/bbs/","host":"m.goumin.com"}
